radioactivedecay/__init__.py
radioactivedecay/converters.py
radioactivedecay/decaydata.py
radioactivedecay/fileio.py
radioactivedecay/inventory.py
radioactivedecay/nuclide.py
radioactivedecay/plots.py
radioactivedecay/utils.py
radioactivedecay/icrp107_ame2020_nubase2020/atomic_masses_sympy_1.8.pickle
radioactivedecay/icrp107_ame2020_nubase2020/atomic_masses_sympy_1.9.pickle
radioactivedecay/icrp107_ame2020_nubase2020/c_inv_scipy.npz
radioactivedecay/icrp107_ame2020_nubase2020/c_inv_sympy_1.8.pickle
radioactivedecay/icrp107_ame2020_nubase2020/c_inv_sympy_1.9.pickle
radioactivedecay/icrp107_ame2020_nubase2020/c_scipy.npz
radioactivedecay/icrp107_ame2020_nubase2020/c_sympy_1.8.pickle
radioactivedecay/icrp107_ame2020_nubase2020/c_sympy_1.9.pickle
radioactivedecay/icrp107_ame2020_nubase2020/decay_consts_sympy_1.8.pickle
radioactivedecay/icrp107_ame2020_nubase2020/decay_consts_sympy_1.9.pickle
radioactivedecay/icrp107_ame2020_nubase2020/decay_data.npz
radioactivedecay/icrp107_ame2020_nubase2020/year_conversion_sympy_1.8.pickle
radioactivedecay/icrp107_ame2020_nubase2020/year_conversion_sympy_1.9.pickle
radioactivedecay-0.6.0.dist-info/LICENSE
radioactivedecay-0.6.0.dist-info/LICENSE.AMDC
radioactivedecay-0.6.0.dist-info/LICENSE.ICRP-07
radioactivedecay-0.6.0.dist-info/METADATA
radioactivedecay-0.6.0.dist-info/WHEEL
radioactivedecay-0.6.0.dist-info/top_level.txt
radioactivedecay-0.6.0.dist-info/RECORD
