Metadata-Version: 2.1
Name: radioactivedecay
Version: 0.6.0
Summary: A Python package for radioactive decay modelling that supports 1252 radionuclides, decay chains, branching, and metastable states.
Author: Thom Lemoine, Ian Cullen, other contributors
Author-email: Alex Malins <github@alexmalinsREMOVETHIS.com>
Project-URL: Changelog, https://github.com/radioactivedecay/radioactivedecay/blob/main/CHANGELOG.md
Project-URL: Discussions, https://github.com/radioactivedecay/radioactivedecay/discussions
Project-URL: Documentation, https://radioactivedecay.github.io
Project-URL: Download, https://pypi.org/project/radioactivedecay/
Project-URL: GitHub, https://github.com/radioactivedecay/radioactivedecay
Project-URL: Homepage, https://github.com/radioactivedecay/radioactivedecay
Project-URL: Issues, https://github.com/radioactivedecay/radioactivedecay/issues
Project-URL: Repository, https://github.com/radioactivedecay/radioactivedecay.git
Keywords: radioactivity,radioactive,decay,nuclides,radiation,physics,radiological protection,health physics,half-life
Classifier: Development Status :: 5 - Production/Stable
Classifier: Intended Audience :: Education
Classifier: Intended Audience :: Science/Research
Classifier: License :: OSI Approved :: MIT License
Classifier: License :: Other/Proprietary License
Classifier: Programming Language :: Python
Classifier: Programming Language :: Python :: 3
Classifier: Programming Language :: Python :: 3 :: Only
Classifier: Programming Language :: Python :: 3.9
Classifier: Programming Language :: Python :: 3.10
Classifier: Programming Language :: Python :: 3.11
Classifier: Programming Language :: Python :: 3.12
Classifier: Programming Language :: Python :: 3.13
Classifier: Operating System :: OS Independent
Classifier: Topic :: Education
Classifier: Topic :: Scientific/Engineering
Requires-Python: >=3.9
License-File: LICENSE
License-File: LICENSE.ICRP-07
License-File: LICENSE.AMDC
Requires-Dist: matplotlib
Requires-Dist: networkx
Requires-Dist: numpy
Requires-Dist: pandas
Requires-Dist: scipy
Requires-Dist: sympy
Provides-Extra: dev
Requires-Dist: black; extra == "dev"
Requires-Dist: build; extra == "dev"
Requires-Dist: coverage; extra == "dev"
Requires-Dist: isort; extra == "dev"
Requires-Dist: mypy; extra == "dev"
Requires-Dist: pandas-stubs; extra == "dev"
Requires-Dist: pylint; extra == "dev"
Requires-Dist: scipy-stubs; extra == "dev"
Provides-Extra: docs
Requires-Dist: sphinx; extra == "docs"
Requires-Dist: sphinx-rtd-theme; extra == "docs"
